{
  "timestamp": "2026-04-12T15:53:20.070Z",
  "processed": 1,
  "posted": 0,
  "relevant": 1,
  "rejected": 0,
  "skipped": 0,
  "actions": [
    {
      "opportunity": {
        "source": "hn-comment",
        "title": "Schedule tasks on the web",
        "url": "https://news.ycombinator.com/item?id=47543679",
        "why": "User looking for AI agent/tool — kbot could be relevant",
        "action": "REVIEW: Consider replying with kbot if genuinely helpful"
      },
      "relevant": true,
      "draft": "The challenge with web-scheduled tasks isn't just the scheduling itself, but reliably handling transient errors and retries across distributed services. Consider implementing a circuit breaker pattern—a design to stop repeatedly calling a failing service—to prevent cascading failures and maintain overall system stability. You'll also want to factor in idempotency—the ability to safely re-run a task without unintended consequences—especially with asynchronous webhooks.",
      "reasoning": "My work in building AI agents and tooling involves scheduling and orchestration, so I can offer a relevant technical perspective.",
      "status": "acted",
      "postResult": {
        "posted": false,
        "error": "already_posted"
      }
    }
  ]
}