{
  "lastRunTimestamps": {
    "pulse": "2026-03-21T08:35:09.085Z",
    "intel": "2026-03-21T08:10:11.020Z",
    "outreach": "2026-03-21T08:15:10.213Z",
    "writing": "2026-03-21T08:10:12.157Z",
    "evolution": "2026-03-21T07:55:45.232Z",
    "opportunities": "2026-03-21T08:35:13.955Z",
    "actions": "2026-03-21T08:06:44.158Z"
  },
  "stats": {
    "totalRuns": 105,
    "totalPulses": 59,
    "totalIntel": 16,
    "totalOutreach": 5,
    "totalWriting": 3,
    "totalEvolution": 4,
    "errorsToday": 0,
    "lastErrorDate": "2026-03-21"
  },
  "knownStars": 3,
  "knownDownloads": 781,
  "hnScore": 1,
  "hnComments": 0
}